digital/readout_seq.v
/*
 This file contains a sequencer for the readout of the 4 pixel camera.
 It can be enabled and reset.
 Note that the enable does not imply a reset.
 */

`ifndef _readout_seq_v_31_
 `define _readout_seq_v_31_


module readout_seq(input logic clk,
		   input logic 	enable, reset,
		   output logic finished,
		   output logic nre1, nre2, adc);

   logic [3:0] 			step;

   assign finished = (step >= 8) ? 1 : 0;
   
   always @(posedge clk)
      if (!finished && enable && !reset) step <= step + 1;
   
   always @(*) begin
      if (reset)
	step <= 0;
      
      case (step)
	0: {nre1, nre2, adc} = 3'b110;
	1: {nre1, nre2, adc} = 3'b010;
	2: {nre1, nre2, adc} = 3'b011;
	3: {nre1, nre2, adc} = 3'b010;
	4: {nre1, nre2, adc} = 3'b110;
	5: {nre1, nre2, adc} = 3'b100;
	6: {nre1, nre2, adc} = 3'b101;
	7: {nre1, nre2, adc} = 3'b100;
	8: {nre1, nre2, adc} = 3'b110;
	default: {nre1, nre2, adc} = 3'b110;
      endcase // case (step)
   end // always @ (*)

   endmodule // readout_seq


 `ifndef _no_testbench_


module readout_seq_tb;
   logic clk, enable, reset, finished, nre1, nre2, adc;

   readout_seq test_seq(clk, enable, reset, finished, nre1, nre2, adc);

   always @(*)
     #1 clk <= !clk;

   initial begin
      $dumpfile("outfiles/out_readout_seq_tb.vcd");
      $dumpvars();
      
      {clk, enable, reset} = 3'b000;
      #5 reset = 1;
      #2 reset = 0;

      #4 enable = 1;
      #20 enable = 0;
      #4 enable = 1;
      #1 reset = 1; #1
      #2 reset = 0;
      #4 enable = 0;

      #4 $finish;
   end // initial begin
   
endmodule // readout_seq_tb


 `endif
`endif //  `ifndef _readout_seq_v_31_

digital/outfiles/out_readout_seq_tb.vcd
$date
	Sun Nov 17 22:51:19 2019
$end
$version
	Icarus Verilog
$end
$timescale
	1s
$end
$scope module readout_seq_tb $end
$var wire 1 ! nre2 $end
$var wire 1 " nre1 $end
$var wire 1 # finished $end
$var wire 1 $ adc $end
$var reg 1 % clk $end
$var reg 1 & enable $end
$var reg 1 ' reset $end
$scope module test_seq $end
$var wire 1 % clk $end
$var wire 1 & enable $end
$var wire 1 ' reset $end
$var wire 1 # finished $end
$var reg 1 $ adc $end
$var reg 1 " nre1 $end
$var reg 1 ! nre2 $end
$var reg 4 ( step [3:0] $end
$upscope $end
$upscope $end
$enddefinitions $end
#0
$dumpvars
bx (
0'
0&
0%
0$
x#
1"
1!
$end
#1
1%
#2
0%
#3
1%
#4
0%
#5
0#
b0 (
1%
1'
#6
0%
#7
1%
0'
#8
0%
#9
1%
#10
0%
#11
0"
b1 (
1%
1&
#12
0%
#13
1$
b10 (
1%
#14
0%
#15
0$
b11 (
1%
#16
0%
#17
1"
b100 (
1%
#18
0%
#19
0!
b101 (
1%
#20
0%
#21
1$
b110 (
1%
#22
0%
#23
0$
b111 (
1%
#24
0%
#25
1#
1!
b1000 (
1%
#26
0%
#27
1%
#28
0%
#29
1%
#30
0%
#31
1%
0&
#32
0%
#33
1%
#34
0%
#35
1%
1&
#36
0#
b0 (
0%
1'
#37
1%
#38
0%
#39
0"
b1 (
1%
0'
#40
0%
#41
1$
b10 (
1%
#42
0%
#43
1%
0&
