digital/fcd_reg.v
/*
 This file contains the register used to count down different values in the camera.
 It has 5 bits, can take data inn and counts down on rising clock edge when enabled.
 It has an output for when the internal data is 0.
 Data set has priority over enable.
 */

`ifndef _fcd_reg_v_28_
 `define _fcd_reg_v_28_


module fcd_reg(input logic clk, enable, dset,
	       input logic [4:0] dread_data,
	       output logic 	 finished);
   
   logic [4:0] 			 data_int;
   
   always @(posedge clk)
     if (dset)
       data_int <= dread_data;
     else if (enable & data_int > 'b0)
       data_int <= data_int - 1;

   assign finished = (data_int == 'b0) ? 1 : 0;
   
endmodule // fcd_reg


`ifndef _no_testbench_


module fcd_reg_tb;
   logic clk, enable, dset, finished;
   logic [4:0] data_in;

   fcd_reg testreg(clk, enable, dset, data_in, finished);

   initial begin
      $dumpfile("outfiles/out_fcd_reg_tb.vcd");
      $dumpvars();

      #1 {clk, enable, dset, data_in} = 7'b0000111;
      #1 {clk, dset} = 2'b11;
      #1 clk = 0;
      #1 {clk, enable, dset} = 3'b110;

      for (int i = 1; i <= 21; i = i + 1) begin
	 #1 clk = !clk;
      end

      #1 {clk, enable} = 2'b10;
      #1 clk = 0;
      #1 clk = 1;

      for (int i = 1; i <= 5; i = i + 1) begin
	 #1 clk = !clk;
      end
      
      #1 {clk, enable, dset} = 3'b111;
      
      for (int i = 1; i <= 5; i = i + 1) begin
	 #1 clk = !clk;
      end

      #1 $finish;
   end // initial begin
   
endmodule // fcd_reg_tb





`endif //  `ifndef _no_testbench_
`endif //  `ifndef _fcd_reg_v_28_

digital/outfiles/out_fcd_reg_tb.vcd
$date
	Mon Oct 28 17:52:27 2019
$end
$version
	Icarus Verilog
$end
$timescale
	1s
$end
$scope module fcd_reg_tb $end
$var wire 1 ! finished $end
$var reg 1 " clk $end
$var reg 5 # data_in [4:0] $end
$var reg 1 $ dset $end
$var reg 1 % enable $end
$scope module testreg $end
$var wire 1 " clk $end
$var wire 5 & dread_data [4:0] $end
$var wire 1 $ dset $end
$var wire 1 % enable $end
$var wire 1 ! finished $end
$var reg 5 ' data_int [4:0] $end
$upscope $end
$scope begin $ivl_for_loop0 $end
$var integer 32 ( i [31:0] $end
$upscope $end
$scope begin $ivl_for_loop1 $end
$var integer 32 ) i [31:0] $end
$upscope $end
$scope begin $ivl_for_loop2 $end
$var integer 32 * i [31:0] $end
$upscope $end
$upscope $end
$enddefinitions $end
#0
$dumpvars
b0 *
b0 )
b0 (
bx '
bx &
x%
x$
bx #
x"
x!
$end
#1
0"
0%
0$
b111 #
b111 &
#2
0!
b111 '
1"
1$
#3
0"
#4
b110 '
b1 (
1"
1%
0$
#5
b10 (
0"
#6
b101 '
b11 (
1"
#7
b100 (
0"
#8
b100 '
b101 (
1"
#9
b110 (
0"
#10
b11 '
b111 (
1"
#11
b1000 (
0"
#12
b10 '
b1001 (
1"
#13
b1010 (
0"
#14
b1 '
b1011 (
1"
#15
b1100 (
0"
#16
1!
b0 '
b1101 (
1"
#17
b1110 (
0"
#18
b1111 (
1"
#19
b10000 (
0"
#20
b10001 (
1"
#21
b10010 (
0"
#22
b10011 (
1"
#23
b10100 (
0"
#24
b10101 (
1"
#25
b10110 (
0"
#26
1"
0%
#27
0"
#28
b1 )
1"
#29
b10 )
0"
#30
b11 )
1"
#31
b100 )
0"
#32
b101 )
1"
#33
b110 )
0"
#34
0!
b111 '
b1 *
1"
1%
1$
#35
b10 *
0"
#36
b11 *
1"
#37
b100 *
0"
#38
b101 *
1"
#39
b110 *
0"
